[
  {
    "inputs": [
      {
        "internalType": "string",
        "name": "_name",
        "type": "string"
      }
    ],
    "stateMutability": "nonpayable",
    "type": "constructor"
  },
  {
    "inputs": [],
    "name": "owner",
    "outputs": [
      {
        "internalType": "address",
        "name": "",
        "type": "address"
      }
    ],
    "stateMutability": "view",
    "type": "function"
  },
  {
    "inputs": [],
    "name": "projectName",
    "outputs": [
      {
        "internalType": "string",
        "name": "",
        "type": "string"
      }
    ],
    "stateMutability": "view",
    "type": "function"
  },
  {
    "inputs": [
      {
        "internalType": "string",
        "name": "_newName",
        "type": "string"
      }
    ],
    "name": "updateName",
    "outputs": [],
    "stateMutability": "nonpayable",
    "type": "function"
  }
] 